mega/__init__.py
mega/crypto.py
mega/errors.py
mega/mega.py
mega_x-1.0.9.dev1.dist-info/LICENSE
mega_x-1.0.9.dev1.dist-info/METADATA
mega_x-1.0.9.dev1.dist-info/WHEEL
mega_x-1.0.9.dev1.dist-info/top_level.txt
mega_x-1.0.9.dev1.dist-info/RECORD
