Metadata-Version: 2.1
Name: mega-x
Version: 1.0.9.dev1
Summary: Python lib for the Mega.co.nz API
Home-page: https://github.com/odwyersoftware/mega.py
Author: O'Dwyer Software
Author-email: hello@odwyer.software
License: Creative Commons Attribution-Noncommercial-Share Alike license
Classifier: Intended Audience :: Developers
Classifier: Operating System :: OS Independent
Classifier: Programming Language :: Python
Classifier: Programming Language :: Python :: 3
Classifier: Topic :: Internet :: WWW/HTTP
License-File: LICENSE
Requires-Dist: requests>=0.10
Requires-Dist: pycryptodome<4.0.0,>=3.9.6
Requires-Dist: pathlib==1.0.1
Requires-Dist: tenacity
Requires-Dist: tqdm
